<?xml version="1.0" encoding="utf-8"?>
<itemcats_get_response>
    <item_cats list="true">
        <item_cat>
            <cid>50004887</cid>
            <is_parent>false</is_parent>
            <name>人文社科类原版书</name>
            <parent_cid>0</parent_cid>
        </item_cat>
        <item_cat>
            <cid>50004889</cid>
            <is_parent>false</is_parent>
            <name>儿童读物原版书</name>
            <parent_cid>0</parent_cid>
        </item_cat>
        <item_cat>
            <cid>50069760</cid>
            <is_parent>true</is_parent>
            <name>品牌保健营养品</name>
            <parent_cid>0</parent_cid>
        </item_cat>
        <item_cat>
            <cid>50069444</cid>
            <is_parent>true</is_parent>
            <name>本地化生活服务</name>
            <parent_cid>0</parent_cid>
        </item_cat>
        <item_cat>
            <cid>50070166</cid>
            <is_parent>false</is_parent>
            <name>枸杞</name>
            <parent_cid>0</parent_cid>
        </item_cat>
        <item_cat>
            <cid>50069762</cid>
            <is_parent>false</is_parent>
            <name>维生素/矿物质</name>
            <parent_cid>0</parent_cid>
        </item_cat>
        <item_cat>
            <cid>50069764</cid>
            <is_parent>false</is_parent>
            <name>维生素A/胡萝卜素</name>
            <parent_cid>0</parent_cid>
        </item_cat>
        <item_cat>
            <cid>50068913</cid>
            <is_parent>false</is_parent>
            <name>尿片/洗护/玩具/推车床</name>
            <parent_cid>0</parent_cid>
        </item_cat>
        <item_cat>
            <cid>50016422</cid>
            <is_parent>false</is_parent>
            <name>粮油/蔬果/干货/速食/水产</name>
            <parent_cid>0</parent_cid>
        </item_cat>
        <item_cat>
            <cid>50000671</cid>
            <is_parent>false</is_parent>
            <name>T恤</name>
            <parent_cid>0</parent_cid>
        </item_cat>
        <item_cat>
            <cid>1625</cid>
            <is_parent>true</is_parent>
            <name>女士内衣/男士内衣/家居服</name>
            <parent_cid>0</parent_cid>
        </item_cat>
        <item_cat>
            <cid>50006843</cid>
            <is_parent>true</is_parent>
            <name>女鞋</name>
            <parent_cid>0</parent_cid>
        </item_cat>
        <item_cat>
            <cid>50016348</cid>
            <is_parent>true</is_parent>
            <name>其它</name>
            <parent_cid>0</parent_cid>
        </item_cat>
        <item_cat>
            <cid>50008090</cid>
            <is_parent>true</is_parent>
            <name>3C数码配件市场</name>
            <parent_cid>0</parent_cid>
        </item_cat>
        <item_cat>
            <cid>1201</cid>
            <is_parent>false</is_parent>
            <name>MP3/MP4/iPod/录音笔</name>
            <parent_cid>0</parent_cid>
        </item_cat>
        <item_cat>
            <cid>50023334</cid>
            <is_parent>true</is_parent>
            <name>OTC药品/医疗器械/隐形眼镜</name>
            <parent_cid>0</parent_cid>
        </item_cat>
        <item_cat>
            <cid>28</cid>
            <is_parent>true</is_parent>
            <name>ZIPPO/瑞士军刀/眼镜</name>
            <parent_cid>0</parent_cid>
        </item_cat>
        <item_cat>
            <cid>50002768</cid>
            <is_parent>true</is_parent>
            <name>个人护理/保健/按摩器材</name>
            <parent_cid>0</parent_cid>
        </item_cat>
        <item_cat>
            <cid>33</cid>
            <is_parent>true</is_parent>
            <name>书籍/杂志/报纸</name>
            <parent_cid>0</parent_cid>
        </item_cat>
        <item_cat>
            <cid>50022562</cid>
            <is_parent>true</is_parent>
            <name>交通工具</name>
            <parent_cid>0</parent_cid>
        </item_cat>
        <item_cat>
            <cid>50008825</cid>
            <is_parent>false</is_parent>
            <name>保健品/滋补品</name>
            <parent_cid>0</parent_cid>
        </item_cat>
        <item_cat>
            <cid>50023800</cid>
            <is_parent>true</is_parent>
            <name>保险</name>
            <parent_cid>0</parent_cid>
        </item_cat>
        <item_cat>
            <cid>50011150</cid>
            <is_parent>false</is_parent>
            <name>其它</name>
            <parent_cid>0</parent_cid>
        </item_cat>
        <item_cat>
            <cid>1410</cid>
            <is_parent>false</is_parent>
            <name>内存卡/U盘/移动存储</name>
            <parent_cid>0</parent_cid>
        </item_cat>
        <item_cat>
            <cid>50007218</cid>
            <is_parent>true</is_parent>
            <name>办公设备/文具/耗材</name>
            <parent_cid>0</parent_cid>
        </item_cat>
        <item_cat>
            <cid>50021243</cid>
            <is_parent>true</is_parent>
            <name>办公设备/耗材/相关服务</name>
            <parent_cid>0</parent_cid>
        </item_cat>
        <item_cat>
            <cid>50012082</cid>
            <is_parent>true</is_parent>
            <name>厨房电器</name>
            <parent_cid>0</parent_cid>
        </item_cat>
        <item_cat>
            <cid>23</cid>
            <is_parent>true</is_parent>
            <name>古董/邮币/字画/收藏</name>
            <parent_cid>0</parent_cid>
        </item_cat>
        <item_cat>
            <cid>50005700</cid>
            <is_parent>false</is_parent>
            <name>品牌手表/流行手表</name>
            <parent_cid>0</parent_cid>
        </item_cat>
        <item_cat>
            <cid>50012081</cid>
            <is_parent>false</is_parent>
            <name>国货精品手机</name>
            <parent_cid>0</parent_cid>
        </item_cat>
        <item_cat>
            <cid>50023391</cid>
            <is_parent>false</is_parent>
            <name>在线数字娱乐</name>
            <parent_cid>0</parent_cid>
        </item_cat>
        <item_cat>
            <cid>50024612</cid>
            <is_parent>true</is_parent>
            <name>外卖/外送/订餐服务（垂直市场）</name>
            <parent_cid>0</parent_cid>
        </item_cat>
        <item_cat>
            <cid>50023501</cid>
            <is_parent>true</is_parent>
            <name>外卖/外送/订餐服务（集市）</name>
            <parent_cid>0</parent_cid>
        </item_cat>
        <item_cat>
            <cid>50021985</cid>
            <is_parent>false</is_parent>
            <name>天气情况</name>
            <parent_cid>0</parent_cid>
        </item_cat>
        <item_cat>
            <cid>35</cid>
            <is_parent>true</is_parent>
            <name>奶粉/辅食/营养品</name>
            <parent_cid>0</parent_cid>
        </item_cat>
        <item_cat>
            <cid>29</cid>
            <is_parent>true</is_parent>
            <name>宠物/宠物食品及用品</name>
            <parent_cid>0</parent_cid>
        </item_cat>
        <item_cat>
            <cid>50008164</cid>
            <is_parent>true</is_parent>
            <name>家具/家具定制/宜家代购</name>
            <parent_cid>0</parent_cid>
        </item_cat>
        <item_cat>
            <cid>50021744</cid>
            <is_parent>true</is_parent>
            <name>家电数码</name>
            <parent_cid>0</parent_cid>
        </item_cat>
        <item_cat>
            <cid>21</cid>
            <is_parent>true</is_parent>
            <name>居家日用/厨房餐饮/卫浴洗浴</name>
            <parent_cid>0</parent_cid>
        </item_cat>
        <item_cat>
            <cid>50023811</cid>
            <is_parent>true</is_parent>
            <name>平板电脑</name>
            <parent_cid>0</parent_cid>
        </item_cat>
        <item_cat>
            <cid>50019780</cid>
            <is_parent>false</is_parent>
            <name>平板电脑/MID</name>
            <parent_cid>0</parent_cid>
        </item_cat>
        <item_cat>
            <cid>50008163</cid>
            <is_parent>true</is_parent>
            <name>床上用品/靠垫/窗帘/布艺</name>
            <parent_cid>0</parent_cid>
        </item_cat>
        <item_cat>
            <cid>50010788</cid>
            <is_parent>true</is_parent>
            <name>彩妆/香水/美发/工具</name>
            <parent_cid>0</parent_cid>
        </item_cat>
        <item_cat>
            <cid>50023392</cid>
            <is_parent>false</is_parent>
            <name>影视</name>
            <parent_cid>0</parent_cid>
        </item_cat>
        <item_cat>
            <cid>50011972</cid>
            <is_parent>true</is_parent>
            <name>影音电器</name>
            <parent_cid>0</parent_cid>
        </item_cat>
        <item_cat>
            <cid>2813</cid>
            <is_parent>true</is_parent>
            <name>成人用品/避孕用品/情趣内衣</name>
            <parent_cid>0</parent_cid>
        </item_cat>
        <item_cat>
            <cid>50023575</cid>
            <is_parent>true</is_parent>
            <name>房产/租房买房</name>
            <parent_cid>0</parent_cid>
        </item_cat>
        <item_cat>
            <cid>14</cid>
            <is_parent>true</is_parent>
            <name>数码相机/摄像机/图形冲印</name>
            <parent_cid>0</parent_cid>
        </item_cat>
        <item_cat>
            <cid>50010404</cid>
            <is_parent>true</is_parent>
            <name>服饰配件/皮带/帽子/围巾</name>
            <parent_cid>0</parent_cid>
        </item_cat>
        <item_cat>
            <cid>50023770</cid>
            <is_parent>false</is_parent>
            <name>汽车</name>
            <parent_cid>0</parent_cid>
        </item_cat>
        <item_cat>
            <cid>50022970</cid>
            <is_parent>true</is_parent>
            <name>汽车/用品/配件/改装/摩托</name>
            <parent_cid>0</parent_cid>
        </item_cat>
        <item_cat>
            <cid>26</cid>
            <is_parent>true</is_parent>
            <name>汽车/配件/改装/摩托/自行车</name>
            <parent_cid>0</parent_cid>
        </item_cat>
        <item_cat>
            <cid>50011740</cid>
            <is_parent>true</is_parent>
            <name>流行男鞋</name>
            <parent_cid>0</parent_cid>
        </item_cat>
        <item_cat>
            <cid>50067029</cid>
            <is_parent>true</is_parent>
            <name>淘花娱乐</name>
            <parent_cid>0</parent_cid>
        </item_cat>
        <item_cat>
            <cid>50008075</cid>
            <is_parent>true</is_parent>
            <name>演出/旅游/吃喝玩乐折扣券</name>
            <parent_cid>0</parent_cid>
        </item_cat>
        <item_cat>
            <cid>50011397</cid>
            <is_parent>true</is_parent>
            <name>珠宝/钻石/翡翠/黄金</name>
            <parent_cid>0</parent_cid>
        </item_cat>
        <item_cat>
            <cid>50012100</cid>
            <is_parent>true</is_parent>
            <name>生活电器</name>
            <parent_cid>0</parent_cid>
        </item_cat>
        <item_cat>
            <cid>50018252</cid>
            <is_parent>true</is_parent>
            <name>电子票务凭证</name>
            <parent_cid>0</parent_cid>
        </item_cat>
        <item_cat>
            <cid>20</cid>
            <is_parent>true</is_parent>
            <name>电玩/配件/游戏/攻略</name>
            <parent_cid>0</parent_cid>
        </item_cat>
        <item_cat>
            <cid>11</cid>
            <is_parent>true</is_parent>
            <name>电脑硬件/台式整机/网络设备</name>
            <parent_cid>0</parent_cid>
        </item_cat>
        <item_cat>
            <cid>30</cid>
            <is_parent>true</is_parent>
            <name>男装</name>
            <parent_cid>0</parent_cid>
        </item_cat>
        <item_cat>
            <cid>50005998</cid>
            <is_parent>true</is_parent>
            <name>益智玩具/童车/童床/书包</name>
            <parent_cid>0</parent_cid>
        </item_cat>
        <item_cat>
            <cid>50008165</cid>
            <is_parent>true</is_parent>
            <name>童装/童鞋/孕妇装</name>
            <parent_cid>0</parent_cid>
        </item_cat>
        <item_cat>
            <cid>50006842</cid>
            <is_parent>true</is_parent>
            <name>箱包皮具/热销女包/男包</name>
            <parent_cid>0</parent_cid>
        </item_cat>
        <item_cat>
            <cid>50016891</cid>
            <is_parent>true</is_parent>
            <name>网游垂直市场根类目</name>
            <parent_cid>0</parent_cid>
        </item_cat>
        <item_cat>
            <cid>40</cid>
            <is_parent>true</is_parent>
            <name>腾讯QQ专区</name>
            <parent_cid>0</parent_cid>
        </item_cat>
        <item_cat>
            <cid>27</cid>
            <is_parent>true</is_parent>
            <name>装潢/灯具/五金/安防/卫浴</name>
            <parent_cid>0</parent_cid>
        </item_cat>
        <item_cat>
            <cid>50010728</cid>
            <is_parent>true</is_parent>
            <name>运动/瑜伽/健身/球迷用品</name>
            <parent_cid>0</parent_cid>
        </item_cat>
        <item_cat>
            <cid>50011699</cid>
            <is_parent>true</is_parent>
            <name>运动服/运动包/颈环配件</name>
            <parent_cid>0</parent_cid>
        </item_cat>
        <item_cat>
            <cid>50010388</cid>
            <is_parent>false</is_parent>
            <name>运动鞋</name>
            <parent_cid>0</parent_cid>
        </item_cat>
        <item_cat>
            <cid>50012029</cid>
            <is_parent>true</is_parent>
            <name>运动鞋new</name>
            <parent_cid>0</parent_cid>
        </item_cat>
        <item_cat>
            <cid>50011949</cid>
            <is_parent>true</is_parent>
            <name>酒店客栈/景点门票/度假旅游</name>
            <parent_cid>0</parent_cid>
        </item_cat>
        <item_cat>
            <cid>50023684</cid>
            <is_parent>false</is_parent>
            <name>鞋子</name>
            <parent_cid>0</parent_cid>
        </item_cat>
        <item_cat>
            <cid>50002766</cid>
            <is_parent>true</is_parent>
            <name>食品/茶叶/零食/特产</name>
            <parent_cid>0</parent_cid>
        </item_cat>
        <item_cat>
            <cid>50013864</cid>
            <is_parent>true</is_parent>
            <name>饰品/流行首饰/时尚饰品新</name>
            <parent_cid>0</parent_cid>
        </item_cat>
        <item_cat>
            <cid>50013929</cid>
            <is_parent>false</is_parent>
            <name>魔兽世界</name>
            <parent_cid>0</parent_cid>
        </item_cat>
        <item_cat>
            <cid>50007216</cid>
            <is_parent>true</is_parent>
            <name>鲜花速递/蛋糕配送/园艺花艺</name>
            <parent_cid>0</parent_cid>
        </item_cat>
        <item_cat>
            <cid>1512</cid>
            <is_parent>false</is_parent>
            <name>手机</name>
            <parent_cid>0</parent_cid>
        </item_cat>
        <item_cat>
            <cid>50014812</cid>
            <is_parent>true</is_parent>
            <name>尿片/洗护/喂哺/推车床</name>
            <parent_cid>0</parent_cid>
        </item_cat>
        <item_cat>
            <cid>50026316</cid>
            <is_parent>false</is_parent>
            <name>茶/酒/冲饮</name>
            <parent_cid>0</parent_cid>
        </item_cat>
        <item_cat>
            <cid>50067207</cid>
            <is_parent>false</is_parent>
            <name>电子凭证</name>
            <parent_cid>0</parent_cid>
        </item_cat>
        <item_cat>
            <cid>50067548</cid>
            <is_parent>true</is_parent>
            <name>其他</name>
            <parent_cid>0</parent_cid>
        </item_cat>
        <item_cat>
            <cid>50070448</cid>
            <is_parent>true</is_parent>
            <name>休闲娱乐/购物卡</name>
            <parent_cid>0</parent_cid>
        </item_cat>
        <item_cat>
            <cid>60118003</cid>
            <is_parent>false</is_parent>
            <name>女装</name>
            <parent_cid>0</parent_cid>
        </item_cat>
        <item_cat>
            <cid>16</cid>
            <is_parent>true</is_parent>
            <name>女装/女士精品</name>
            <parent_cid>0</parent_cid>
        </item_cat>
        <item_cat>
            <cid>50068242</cid>
            <is_parent>false</is_parent>
            <name>彩妆/香水/美妆工具</name>
            <parent_cid>0</parent_cid>
        </item_cat>
        <item_cat>
            <cid>50024971</cid>
            <is_parent>false</is_parent>
            <name>新车/二手车</name>
            <parent_cid>0</parent_cid>
        </item_cat>
        <item_cat>
            <cid>60372003</cid>
            <is_parent>true</is_parent>
            <name>景点门票/度假线路/旅游服务</name>
            <parent_cid>0</parent_cid>
        </item_cat>
        <item_cat>
            <cid>50025110</cid>
            <is_parent>true</is_parent>
            <name>电影/演出/体育赛事</name>
            <parent_cid>0</parent_cid>
        </item_cat>
        <item_cat>
            <cid>50014811</cid>
            <is_parent>true</is_parent>
            <name>网店/网店服务/软件</name>
            <parent_cid>0</parent_cid>
        </item_cat>
        <item_cat>
            <cid>50068240</cid>
            <is_parent>true</is_parent>
            <name>美发护发/假发</name>
            <parent_cid>0</parent_cid>
        </item_cat>
        <item_cat>
            <cid>50070447</cid>
            <is_parent>true</is_parent>
            <name>餐饮美食/面包券</name>
            <parent_cid>0</parent_cid>
        </item_cat>
    </item_cats>
</itemcats_get_response>
        <!--vsandbox067144.cm4.tbsite.net-->
